{
  "updatedAt": "2026-05-02T10:15:14.242Z",
  "totalDraws": 17114,
  "numberFreq": {
    "1": 5366,
    "2": 5316,
    "3": 5333,
    "4": 5460,
    "5": 5460,
    "6": 5366,
    "7": 5386,
    "8": 5303,
    "9": 5270,
    "10": 5399,
    "11": 5343,
    "12": 5361,
    "13": 5320,
    "14": 5409,
    "15": 5376,
    "16": 5325,
    "17": 5449,
    "18": 5327,
    "19": 5239,
    "20": 5410,
    "21": 5353,
    "22": 5278,
    "23": 5424,
    "24": 5310,
    "25": 5414,
    "26": 5415,
    "27": 5446,
    "28": 5248,
    "29": 5452,
    "30": 5415,
    "31": 5380,
    "32": 5403,
    "33": 5256,
    "34": 5348,
    "35": 5400,
    "36": 5356,
    "37": 5464,
    "38": 5446,
    "39": 5419,
    "40": 5411,
    "41": 5404,
    "42": 5413,
    "43": 5407,
    "44": 5376,
    "45": 5341,
    "46": 5357,
    "47": 5511,
    "48": 5329,
    "49": 5370,
    "50": 5327,
    "51": 5291,
    "52": 5412,
    "53": 5392,
    "54": 5331,
    "55": 5429,
    "56": 5357,
    "57": 5479,
    "58": 5508,
    "59": 5270,
    "60": 5401,
    "61": 5519,
    "62": 5496,
    "63": 5379,
    "64": 5271,
    "65": 5360,
    "66": 5329,
    "67": 5398,
    "68": 5345,
    "69": 5465,
    "70": 5385
  },
  "luckyFreq": {
    "1": 264,
    "2": 223,
    "3": 203,
    "4": 250,
    "5": 265,
    "6": 240,
    "7": 254,
    "8": 241,
    "9": 235,
    "10": 256,
    "11": 240,
    "12": 273,
    "13": 237,
    "14": 217,
    "15": 243,
    "16": 228,
    "17": 234,
    "18": 267,
    "19": 231,
    "20": 256,
    "21": 236,
    "22": 259,
    "23": 238,
    "24": 244,
    "25": 235,
    "26": 227,
    "27": 247,
    "28": 216,
    "29": 268,
    "30": 233,
    "31": 227,
    "32": 245,
    "33": 275,
    "34": 250,
    "35": 269,
    "36": 237,
    "37": 262,
    "38": 225,
    "39": 235,
    "40": 240,
    "41": 256,
    "42": 259,
    "43": 244,
    "44": 238,
    "45": 252,
    "46": 229,
    "47": 253,
    "48": 242,
    "49": 229,
    "50": 236,
    "51": 265,
    "52": 236,
    "53": 254,
    "54": 252,
    "55": 248,
    "56": 213,
    "57": 237,
    "58": 259,
    "59": 241,
    "60": 244,
    "61": 260,
    "62": 223,
    "63": 247,
    "64": 262,
    "65": 262,
    "66": 245,
    "67": 287,
    "68": 212,
    "69": 263,
    "70": 241
  },
  "sumBinFreq": {
    "b1": 2,
    "b2": 1,
    "b3": 58,
    "b4": 102,
    "b5": 986,
    "b6": 1460,
    "b7": 2556,
    "b8": 5221,
    "b9": 6728
  },
  "recent": {
    "10": {
      "numberFreq": {
        "1": 4,
        "2": 2,
        "3": 4,
        "4": 1,
        "5": 2,
        "6": 4,
        "7": 3,
        "8": 5,
        "9": 4,
        "10": 1,
        "11": 6,
        "12": 3,
        "13": 5,
        "14": 2,
        "15": 3,
        "16": 3,
        "17": 3,
        "18": 4,
        "19": 3,
        "20": 5,
        "21": 2,
        "22": 3,
        "23": 3,
        "24": 2,
        "25": 4,
        "26": 4,
        "27": 5,
        "28": 4,
        "29": 5,
        "30": 6,
        "31": 3,
        "32": 4,
        "33": 2,
        "34": 5,
        "35": 3,
        "36": 3,
        "37": 2,
        "38": 3,
        "39": 2,
        "40": 5,
        "41": 0,
        "42": 3,
        "43": 4,
        "44": 0,
        "45": 2,
        "46": 1,
        "47": 2,
        "48": 1,
        "49": 3,
        "50": 3,
        "51": 6,
        "52": 2,
        "53": 4,
        "54": 2,
        "55": 3,
        "56": 3,
        "57": 1,
        "58": 5,
        "59": 3,
        "60": 3,
        "61": 4,
        "62": 2,
        "63": 1,
        "64": 3,
        "65": 4,
        "66": 2,
        "67": 4,
        "68": 2,
        "69": 4,
        "70": 6
      },
      "luckyFreq": {
        "1": 0,
        "2": 0,
        "3": 0,
        "4": 0,
        "5": 0,
        "6": 0,
        "7": 1,
        "8": 0,
        "9": 0,
        "10": 0,
        "11": 1,
        "12": 0,
        "13": 0,
        "14": 0,
        "15": 0,
        "16": 0,
        "17": 1,
        "18": 2,
        "19": 1,
        "20": 0,
        "21": 0,
        "22": 0,
        "23": 0,
        "24": 0,
        "25": 1,
        "26": 0,
        "27": 0,
        "28": 1,
        "29": 1,
        "30": 0,
        "31": 0,
        "32": 1,
        "33": 0,
        "34": 0,
        "35": 0,
        "36": 0,
        "37": 0,
        "38": 0,
        "39": 0,
        "40": 0,
        "41": 0,
        "42": 0,
        "43": 0,
        "44": 0,
        "45": 0,
        "46": 0,
        "47": 0,
        "48": 0,
        "49": 0,
        "50": 0,
        "51": 0,
        "52": 0,
        "53": 0,
        "54": 0,
        "55": 0,
        "56": 0,
        "57": 0,
        "58": 0,
        "59": 0,
        "60": 0,
        "61": 0,
        "62": 0,
        "63": 0,
        "64": 0,
        "65": 0,
        "66": 0,
        "67": 0,
        "68": 0,
        "69": 0,
        "70": 0
      },
      "sumBinFreq": {
        "b1": 0,
        "b2": 0,
        "b3": 0,
        "b4": 0,
        "b5": 0,
        "b6": 2,
        "b7": 3,
        "b8": 2,
        "b9": 3
      }
    },
    "20": {
      "numberFreq": {
        "1": 6,
        "2": 3,
        "3": 7,
        "4": 4,
        "5": 5,
        "6": 6,
        "7": 7,
        "8": 10,
        "9": 5,
        "10": 5,
        "11": 8,
        "12": 9,
        "13": 9,
        "14": 6,
        "15": 5,
        "16": 4,
        "17": 8,
        "18": 6,
        "19": 7,
        "20": 8,
        "21": 4,
        "22": 6,
        "23": 7,
        "24": 6,
        "25": 6,
        "26": 11,
        "27": 10,
        "28": 6,
        "29": 7,
        "30": 11,
        "31": 8,
        "32": 7,
        "33": 5,
        "34": 9,
        "35": 5,
        "36": 4,
        "37": 6,
        "38": 6,
        "39": 7,
        "40": 6,
        "41": 5,
        "42": 8,
        "43": 5,
        "44": 1,
        "45": 3,
        "46": 3,
        "47": 6,
        "48": 3,
        "49": 7,
        "50": 6,
        "51": 8,
        "52": 4,
        "53": 8,
        "54": 3,
        "55": 6,
        "56": 5,
        "57": 5,
        "58": 9,
        "59": 7,
        "60": 6,
        "61": 6,
        "62": 4,
        "63": 7,
        "64": 7,
        "65": 10,
        "66": 7,
        "67": 7,
        "68": 2,
        "69": 7,
        "70": 10
      },
      "luckyFreq": {
        "1": 0,
        "2": 0,
        "3": 0,
        "4": 0,
        "5": 0,
        "6": 0,
        "7": 1,
        "8": 0,
        "9": 0,
        "10": 0,
        "11": 1,
        "12": 0,
        "13": 0,
        "14": 0,
        "15": 0,
        "16": 0,
        "17": 1,
        "18": 2,
        "19": 1,
        "20": 1,
        "21": 1,
        "22": 0,
        "23": 0,
        "24": 0,
        "25": 1,
        "26": 1,
        "27": 1,
        "28": 2,
        "29": 1,
        "30": 0,
        "31": 0,
        "32": 1,
        "33": 0,
        "34": 0,
        "35": 0,
        "36": 0,
        "37": 0,
        "38": 1,
        "39": 0,
        "40": 0,
        "41": 0,
        "42": 0,
        "43": 0,
        "44": 0,
        "45": 0,
        "46": 0,
        "47": 0,
        "48": 0,
        "49": 1,
        "50": 0,
        "51": 0,
        "52": 0,
        "53": 2,
        "54": 0,
        "55": 0,
        "56": 0,
        "57": 0,
        "58": 1,
        "59": 0,
        "60": 0,
        "61": 0,
        "62": 0,
        "63": 0,
        "64": 0,
        "65": 0,
        "66": 0,
        "67": 0,
        "68": 0,
        "69": 0,
        "70": 0
      },
      "sumBinFreq": {
        "b1": 0,
        "b2": 0,
        "b3": 0,
        "b4": 0,
        "b5": 2,
        "b6": 2,
        "b7": 4,
        "b8": 5,
        "b9": 7
      }
    },
    "30": {
      "numberFreq": {
        "1": 9,
        "2": 5,
        "3": 11,
        "4": 8,
        "5": 10,
        "6": 10,
        "7": 10,
        "8": 12,
        "9": 9,
        "10": 8,
        "11": 10,
        "12": 13,
        "13": 9,
        "14": 9,
        "15": 10,
        "16": 6,
        "17": 9,
        "18": 9,
        "19": 11,
        "20": 11,
        "21": 7,
        "22": 11,
        "23": 12,
        "24": 11,
        "25": 8,
        "26": 14,
        "27": 12,
        "28": 9,
        "29": 10,
        "30": 13,
        "31": 10,
        "32": 9,
        "33": 7,
        "34": 15,
        "35": 8,
        "36": 6,
        "37": 7,
        "38": 11,
        "39": 13,
        "40": 10,
        "41": 11,
        "42": 9,
        "43": 10,
        "44": 6,
        "45": 5,
        "46": 7,
        "47": 9,
        "48": 7,
        "49": 14,
        "50": 9,
        "51": 8,
        "52": 7,
        "53": 9,
        "54": 8,
        "55": 8,
        "56": 7,
        "57": 7,
        "58": 12,
        "59": 11,
        "60": 8,
        "61": 9,
        "62": 6,
        "63": 9,
        "64": 8,
        "65": 13,
        "66": 10,
        "67": 11,
        "68": 3,
        "69": 11,
        "70": 16
      },
      "luckyFreq": {
        "1": 0,
        "2": 0,
        "3": 0,
        "4": 1,
        "5": 0,
        "6": 0,
        "7": 1,
        "8": 0,
        "9": 0,
        "10": 1,
        "11": 1,
        "12": 0,
        "13": 0,
        "14": 0,
        "15": 0,
        "16": 0,
        "17": 1,
        "18": 2,
        "19": 1,
        "20": 1,
        "21": 1,
        "22": 0,
        "23": 0,
        "24": 1,
        "25": 1,
        "26": 1,
        "27": 1,
        "28": 2,
        "29": 1,
        "30": 0,
        "31": 0,
        "32": 1,
        "33": 0,
        "34": 1,
        "35": 0,
        "36": 0,
        "37": 0,
        "38": 2,
        "39": 0,
        "40": 0,
        "41": 1,
        "42": 0,
        "43": 0,
        "44": 0,
        "45": 0,
        "46": 2,
        "47": 0,
        "48": 1,
        "49": 1,
        "50": 0,
        "51": 0,
        "52": 0,
        "53": 2,
        "54": 0,
        "55": 0,
        "56": 0,
        "57": 1,
        "58": 1,
        "59": 0,
        "60": 0,
        "61": 0,
        "62": 0,
        "63": 0,
        "64": 0,
        "65": 0,
        "66": 0,
        "67": 0,
        "68": 0,
        "69": 0,
        "70": 0
      },
      "sumBinFreq": {
        "b1": 0,
        "b2": 0,
        "b3": 0,
        "b4": 0,
        "b5": 4,
        "b6": 2,
        "b7": 4,
        "b8": 10,
        "b9": 10
      }
    }
  },
  "sumBins": [
    {
      "key": "b1",
      "label": "253-486",
      "min": 253,
      "max": 486,
      "limited1PerDraw": true
    },
    {
      "key": "b2",
      "label": "487-512",
      "min": 487,
      "max": 512,
      "limited1PerDraw": true
    },
    {
      "key": "b3",
      "label": "513-568",
      "min": 513,
      "max": 568,
      "limited1PerDraw": false
    },
    {
      "key": "b4",
      "label": "569-594",
      "min": 569,
      "max": 594,
      "limited1PerDraw": false
    },
    {
      "key": "b5",
      "label": "595-663",
      "min": 595,
      "max": 663,
      "limited1PerDraw": false
    },
    {
      "key": "b6",
      "label": "664-700",
      "min": 664,
      "max": 700,
      "limited1PerDraw": false
    },
    {
      "key": "b7",
      "label": "701-740",
      "min": 701,
      "max": 740,
      "limited1PerDraw": false
    },
    {
      "key": "b8",
      "label": "741-803",
      "min": 741,
      "max": 803,
      "limited1PerDraw": false
    },
    {
      "key": "b9",
      "label": "804-1309",
      "min": 804,
      "max": 1309,
      "limited1PerDraw": false
    }
  ],
  "health": {
    "apiCandidates": [
      "https://api.bepick.io/keno/get/",
      "https://api.bepick.net/keno/get/"
    ],
    "interval": "https://bepick.net/game/interval/speedkeno",
    "crosscheck": {
      "checked": 0,
      "matched": 0,
      "mismatched": 0
    },
    "note": "BEPICK API provides latest 30 results. Repo data grows forward as Actions runs."
  }
}
